flowdas.oliver-0.4.0.dist-info/WHEEL
flowdas.oliver-0.4.0.dist-info/RECORD
flowdas.oliver-0.4.0.dist-info/top_level.txt
flowdas.oliver-0.4.0.dist-info/entry_points.txt
flowdas.oliver-0.4.0.dist-info/LICENSE
flowdas.oliver-0.4.0.dist-info/METADATA
flowdas/oliver/testing.py
flowdas/oliver/parser.cpython-36m-x86_64-linux-gnu.so
flowdas/oliver/__init__.py
flowdas/oliver/app.py
flowdas/oliver/gworker.py
flowdas/oliver/web.py
flowdas/oliver/base.py
flowdas/oliver/openapi.py
