Metadata-Version: 2.1
Name: flowdas.oliver
Version: 0.4.0
Summary: Oliver: A pretty fast WSGI server
Home-page: https://bitbucket.org/flowdas/oliver
Author: Flowdas Inc.
Author-email: prospero@flowdas.com
License: MPL 2.0
Keywords: http,wsgi,server,gevent,asynchronous
Platform: UNKNOWN
Classifier: Development Status :: 5 - Production/Stable
Classifier: Intended Audience :: Developers
Classifier: Topic :: Software Development :: Libraries :: Python Modules
Classifier: License :: OSI Approved :: Mozilla Public License 2.0 (MPL 2.0)
Classifier: Operating System :: MacOS :: MacOS X
Classifier: Operating System :: POSIX
Classifier: Programming Language :: Python :: 3
Classifier: Programming Language :: Python :: 3.4
Classifier: Programming Language :: Python :: 3.5
Classifier: Programming Language :: Python :: 3.6
Classifier: Programming Language :: Python :: 3.7
Classifier: Topic :: Internet
Classifier: Topic :: Utilities
Classifier: Topic :: Software Development :: Libraries :: Python Modules
Classifier: Topic :: Internet :: WWW/HTTP
Classifier: Topic :: Internet :: WWW/HTTP :: WSGI
Classifier: Topic :: Internet :: WWW/HTTP :: WSGI :: Server
Classifier: Topic :: Internet :: WWW/HTTP :: Dynamic Content
Requires-Dist: flowdas
Requires-Dist: gunicorn (>=19.7)
Requires-Dist: gevent (>=1.2)
Requires-Dist: click (<6.8,>=6.7)
Requires-Dist: falcon (>=1.2)
Requires-Dist: setproctitle (>=1.1)
Requires-Dist: PyYAML
Provides-Extra: test
Requires-Dist: pytest (>=3.1) ; extra == 'test'
Requires-Dist: coverage (>=4.4) ; extra == 'test'
Requires-Dist: tox (>=2.7) ; extra == 'test'
